AUTHORS.rst
CONTRIBUTING.rst
HISTORY.rst
LICENSE
MANIFEST.in
README.rst
requirements.txt
setup.cfg
setup.py
analyzerstrategies/__init__.py
analyzerstrategies/periodStrategy.py
analyzerstrategies/smaPortfolioStrategy.py
analyzerstrategies/smaStrategy.py
analyzerstrategies/zscoreMomentumPortfolioStrategy.py
analyzerstrategies/zscorePortfolioStrategy.py
analyzerstrategies.egg-info/PKG-INFO
analyzerstrategies.egg-info/SOURCES.txt
analyzerstrategies.egg-info/dependency_links.txt
analyzerstrategies.egg-info/not-zip-safe
analyzerstrategies.egg-info/top_level.txt