Metadata-Version: 1.1
Name: analyzerstrategies
Version: 0.1.4
Summary: Strategies for Analyzer
Home-page: https://github.com/llazzaro/analyzerstrategies
Author: Leonardo Lazzaro
Author-email: lazzaroleonardo@gmail.com
License: BSD
Keywords: analyzerstrategies
Platform: UNKNOWN
Classifier: Development Status :: 2 - Pre-Alpha
Classifier: Intended Audience :: Developers
Classifier: License :: OSI Approved :: BSD License
Classifier: Natural Language :: English
Classifier: Programming Language :: Python :: 2
Classifier: Programming Language :: Python :: 2.6
Classifier: Programming Language :: Python :: 2.7
Classifier: Programming Language :: Python :: 3
Classifier: Programming Language :: Python :: 3.3
Classifier: Programming Language :: Python :: 3.4
